<Survey>
  <!-- The Short name is used when the survey is part of a list -->
  <ShortName> 4850MHz,GB6/PMN,PMN,GB6,GB6 (4850MHz) </ShortName>
  
  <!-- This is a more complete descriptive name -->
  <Name>4850 MHz Survey - GB6/PMN</Name>
  
  <!-- A text description of the survey.  This may include HTML and
       if so would normally be included in a CDATA element. -->
  <Description>
   <![CDATA[
The 4850MHz data is a 
combination of data from three different surveys: Parkes-MIT-NRAO (PMN) 
Southern (-88&#176 to -37&#176 declination) and tropical surveys (-29&#176
to -9&#176 declination, and (86+87) Green Bank survey (0&#176 to +75&#176 
declination).   The data contains gaps between -27&#176 to -39&#176,
-9&#176 to 0&#176, and 
+77&#176 to +90&#176 declination. 

The 4850MHz survey data were obtained by tape from J.J. Condon and are comprised 
of 576 images and are used by permission.  Full information pertaining to 
these surveys are found in the references.<P>
]]>
 
  </Description>
  
  <!-- These settings are used where the user may not have made an explicit selection
       and where no system defaults exist.
    -->
  <Settings>
    <!-- The scale of this image -->
    <Scale> .01111111138</Scale>
  </Settings>
  
  <!-- The MetaTable includes a set of standard metadata about the survey -->
  <MetaTable>
    <Provenance>
      <![CDATA[
        NRAO, generated by J.J. Condon, J.J. Broderick and G.A. Seielstad, Douglas, K., and Gregory, P.C.
      ]]>
    </Provenance>
    <Copyright> Used by permission of J.J. Condon</Copyright>
    <Regime>     Radio              </Regime>
    <NSurvey>    2                  </NSurvey>
    <Frequency>  4850 MHz continuum </Frequency>
    <Bandpass>   4550 - 5150 MHz    </Bandpass>
    <Coverage>   RA: 0d - 360d, DEC: -88d to +75d </Coverage>
    <PixelScale> 1'/pixel (PMN), and 0.66' /pixel ((86+87) GB)</PixelScale>
    <PixelUnits> janskies/beam  (ca. 200,000 beams/steradian) </PixelUnits>
    <Resolution> 3.5' FWHM             </Resolution>
    <CoordinateSystem> Equatorial    </CoordinateSystem>
    <Equinox>    1950                </Equinox>
    <Epoch>  <![CDATA[
    Greenbank: 1986-11,1987-10<br>
    PMN:       1990
    ]]>
    </Epoch>
    <Projection> Orthographic (SIN)  </Projection>
    <Reference> 
       <![CDATA[
         Condon, <i>et al.</i>, <a href="http://adsabs.harvard.edu/abs/1991AJ....102.2041C">1991</a>;
         <a href="http://adsabs.harvard.edu/abs/1993AJ....106.1095C">1993</a>,
         <a href="http://adsabs.harvard.edu/abs/1994AJ....107.1829C">1994</a>
       ]]>
    </Reference>
  </MetaTable>
  
  <!-- Online text is displayed in a HTML rendering of output.
       The online text can include the special strings $ra,$dec and $size
       which are replaced by the J2000 RA, J2000 Dec or size in degrees
       of the search just completed.  If online text is present
       it will usually contain XML and should be within a CDATA element.
    -->
  <OnlineText/>

  <!-- The text included in the FITS element should be added to the FITS
       header for the image generated by the file.  Note that we
       do not include the MetaTable information which may be extracted
       from the MetaTable elements.  We include the FITS element in
       a CDATA to preserve any special characters and spacing
    -->
  <FITS>
<![CDATA[
SURVEY  = '4850MHz '
TELESCOP= 'MULTIPLE'
INSTRUME= '7-BEAM  '
OBSERVER= 'CONDON  '
DATE-OBS= '22/02/90'
DATE-MAP= '16/05/91'
BUNIT   = 'JY/BEAM '
COMMENT  These data comprise data from three surveys:
COMMENT      Parkes-MIT-NRAO Southern   (-88 to -37 degrees declination)
COMMENT      Parkes-MIT-NRAO Tropical   (-29 to -9  degrees declination)
COMMENT      (86+87) Green Bank         (0   to +75 degrees declination)
]]>
  </FITS>
  
  <!-- The Images area includes descriptors of the images in the survey
       and replaces the config file in the previous version of SkyView.
       Each Image line has 4 tokens: filename, J2000 RA, J2000 Dec and
       Epoch of the image.
    -->
  <Images>
    <!-- The Image factory is the name of a class implementing the ImageFactory
         interface that can be used to create an image given the full
	 file name. -->
    <ImageFactory>
         skyview.survey.CachingImageFactory
    </ImageFactory>
    
    <!-- The CachingImageFactory uses a complex spell with many fields
         which may be repeated from image to image.  We provide both
	 a prefix and suffix.
      -->
    <SpellPrefix>http://skyview.gsfc.nasa.gov/surveys/4850mhz/</SpellPrefix>
    <SpellSuffix>,Sin,J2000,1024,1024,0.0111111,0.011111</SpellSuffix>
    
    <!-- The image size gives the minimum dimension of an image. -->
    <ImageSize> 15 </ImageSize>
    
    <Image> 4850GB_1.fits,4850GB_1.fits,5.00000,-0.0017   5.00000   -0.0017   1990.00 </Image>
    <Image> 4850GB_10.fits,4850GB_10.fits,15.00000,9.9983   15.00000   9.9983   1990.00 </Image>
    <Image> 4850GB_100.fits,4850GB_100.fits,124.99999,29.9983   124.99999   29.9983   1990.00 </Image>
    <Image> 4850GB_101.fits,4850GB_101.fits,124.99999,39.9983   124.99999   39.9983   1990.00 </Image>
    <Image> 4850GB_102.fits,4850GB_102.fits,124.99999,49.9983   124.99999   49.9983   1990.00 </Image>
    <Image> 4850GB_103.fits,4850GB_103.fits,124.99999,59.9983   124.99999   59.9983   1990.00 </Image>
    <Image> 4850GB_104.fits,4850GB_104.fits,124.99999,69.9983   124.99999   69.9983   1990.00 </Image>
    <Image> 4850GB_105.fits,4850GB_105.fits,135.00000,-0.0017   135.00000   -0.0017   1990.00 </Image>
    <Image> 4850GB_106.fits,4850GB_106.fits,135.00000,9.9983   135.00000   9.9983   1990.00 </Image>
    <Image> 4850GB_107.fits,4850GB_107.fits,135.00000,19.9983   135.00000   19.9983   1990.00 </Image>
    <Image> 4850GB_108.fits,4850GB_108.fits,135.00000,29.9983   135.00000   29.9983   1990.00 </Image>
    <Image> 4850GB_109.fits,4850GB_109.fits,135.00000,39.9983   135.00000   39.9983   1990.00 </Image>
    <Image> 4850GB_11.fits,4850GB_11.fits,15.00000,19.9983   15.00000   19.9983   1990.00 </Image>
    <Image> 4850GB_110.fits,4850GB_110.fits,135.00000,49.9983   135.00000   49.9983   1990.00 </Image>
    <Image> 4850GB_111.fits,4850GB_111.fits,135.00000,59.9983   135.00000   59.9983   1990.00 </Image>
    <Image> 4850GB_112.fits,4850GB_112.fits,135.00000,69.9983   135.00000   69.9983   1990.00 </Image>
    <Image> 4850GB_113.fits,4850GB_113.fits,145.00000,-0.0017   145.00000   -0.0017   1990.00 </Image>
    <Image> 4850GB_114.fits,4850GB_114.fits,145.00000,9.9983   145.00000   9.9983   1990.00 </Image>
    <Image> 4850GB_115.fits,4850GB_115.fits,145.00000,19.9983   145.00000   19.9983   1990.00 </Image>
    <Image> 4850GB_116.fits,4850GB_116.fits,145.00000,29.9983   145.00000   29.9983   1990.00 </Image>
    <Image> 4850GB_117.fits,4850GB_117.fits,145.00000,39.9983   145.00000   39.9983   1990.00 </Image>
    <Image> 4850GB_118.fits,4850GB_118.fits,145.00000,49.9983   145.00000   49.9983   1990.00 </Image>
    <Image> 4850GB_119.fits,4850GB_119.fits,145.00000,59.9983   145.00000   59.9983   1990.00 </Image>
    <Image> 4850GB_12.fits,4850GB_12.fits,15.00000,29.9983   15.00000   29.9983   1990.00 </Image>
    <Image> 4850GB_120.fits,4850GB_120.fits,145.00000,69.9983   145.00000   69.9983   1990.00 </Image>
    <Image> 4850GB_121.fits,4850GB_121.fits,155.00000,-0.0017   155.00000   -0.0017   1990.00 </Image>
    <Image> 4850GB_122.fits,4850GB_122.fits,155.00000,9.9983   155.00000   9.9983   1990.00 </Image>
    <Image> 4850GB_123.fits,4850GB_123.fits,155.00000,19.9983   155.00000   19.9983   1990.00 </Image>
    <Image> 4850GB_124.fits,4850GB_124.fits,155.00000,29.9983   155.00000   29.9983   1990.00 </Image>
    <Image> 4850GB_125.fits,4850GB_125.fits,155.00000,39.9983   155.00000   39.9983   1990.00 </Image>
    <Image> 4850GB_126.fits,4850GB_126.fits,155.00000,49.9983   155.00000   49.9983   1990.00 </Image>
    <Image> 4850GB_127.fits,4850GB_127.fits,155.00000,59.9983   155.00000   59.9983   1990.00 </Image>
    <Image> 4850GB_128.fits,4850GB_128.fits,155.00000,69.9983   155.00000   69.9983   1990.00 </Image>
    <Image> 4850GB_129.fits,4850GB_129.fits,165.00000,-0.0017   165.00000   -0.0017   1990.00 </Image>
    <Image> 4850GB_13.fits,4850GB_13.fits,15.00000,39.9983   15.00000   39.9983   1990.00 </Image>
    <Image> 4850GB_130.fits,4850GB_130.fits,165.00000,9.9983   165.00000   9.9983   1990.00 </Image>
    <Image> 4850GB_131.fits,4850GB_131.fits,165.00000,19.9983   165.00000   19.9983   1990.00 </Image>
    <Image> 4850GB_132.fits,4850GB_132.fits,165.00000,29.9983   165.00000   29.9983   1990.00 </Image>
    <Image> 4850GB_133.fits,4850GB_133.fits,165.00000,39.9983   165.00000   39.9983   1990.00 </Image>
    <Image> 4850GB_134.fits,4850GB_134.fits,165.00000,49.9983   165.00000   49.9983   1990.00 </Image>
    <Image> 4850GB_135.fits,4850GB_135.fits,165.00000,59.9983   165.00000   59.9983   1990.00 </Image>
    <Image> 4850GB_136.fits,4850GB_136.fits,165.00000,69.9983   165.00000   69.9983   1990.00 </Image>
    <Image> 4850GB_137.fits,4850GB_137.fits,175.00000,-0.0017   175.00000   -0.0017   1990.00 </Image>
    <Image> 4850GB_138.fits,4850GB_138.fits,175.00000,9.9983   175.00000   9.9983   1990.00 </Image>
    <Image> 4850GB_139.fits,4850GB_139.fits,175.00000,19.9983   175.00000   19.9983   1990.00 </Image>
    <Image> 4850GB_14.fits,4850GB_14.fits,15.00000,49.9983   15.00000   49.9983   1990.00 </Image>
    <Image> 4850GB_140.fits,4850GB_140.fits,175.00000,29.9983   175.00000   29.9983   1990.00 </Image>
    <Image> 4850GB_141.fits,4850GB_141.fits,175.00000,39.9983   175.00000   39.9983   1990.00 </Image>
    <Image> 4850GB_142.fits,4850GB_142.fits,175.00000,49.9983   175.00000   49.9983   1990.00 </Image>
    <Image> 4850GB_143.fits,4850GB_143.fits,175.00000,59.9983   175.00000   59.9983   1990.00 </Image>
    <Image> 4850GB_144.fits,4850GB_144.fits,175.00000,69.9983   175.00000   69.9983   1990.00 </Image>
    <Image> 4850GB_145.fits,4850GB_145.fits,-175.00000,-0.0017   -175.00000   -0.0017   1990.00 </Image>
    <Image> 4850GB_146.fits,4850GB_146.fits,-175.00000,9.9983   -175.00000   9.9983   1990.00 </Image>
    <Image> 4850GB_147.fits,4850GB_147.fits,-175.00000,19.9983   -175.00000   19.9983   1990.00 </Image>
    <Image> 4850GB_148.fits,4850GB_148.fits,-175.00000,29.9983   -175.00000   29.9983   1990.00 </Image>
    <Image> 4850GB_149.fits,4850GB_149.fits,-175.00000,39.9983   -175.00000   39.9983   1990.00 </Image>
    <Image> 4850GB_15.fits,4850GB_15.fits,15.00000,59.9983   15.00000   59.9983   1990.00 </Image>
    <Image> 4850GB_150.fits,4850GB_150.fits,-175.00000,49.9983   -175.00000   49.9983   1990.00 </Image>
    <Image> 4850GB_151.fits,4850GB_151.fits,-175.00000,59.9983   -175.00000   59.9983   1990.00 </Image>
    <Image> 4850GB_152.fits,4850GB_152.fits,-175.00000,69.9983   -175.00000   69.9983   1990.00 </Image>
    <Image> 4850GB_153.fits,4850GB_153.fits,-165.00000,-0.0017   -165.00000   -0.0017   1990.00 </Image>
    <Image> 4850GB_154.fits,4850GB_154.fits,-165.00000,9.9983   -165.00000   9.9983   1990.00 </Image>
    <Image> 4850GB_155.fits,4850GB_155.fits,-165.00000,19.9983   -165.00000   19.9983   1990.00 </Image>
    <Image> 4850GB_156.fits,4850GB_156.fits,-165.00000,29.9983   -165.00000   29.9983   1990.00 </Image>
    <Image> 4850GB_157.fits,4850GB_157.fits,-165.00000,39.9983   -165.00000   39.9983   1990.00 </Image>
    <Image> 4850GB_158.fits,4850GB_158.fits,-165.00000,49.9983   -165.00000   49.9983   1990.00 </Image>
    <Image> 4850GB_159.fits,4850GB_159.fits,-165.00000,59.9983   -165.00000   59.9983   1990.00 </Image>
    <Image> 4850GB_16.fits,4850GB_16.fits,15.00000,69.9983   15.00000   69.9983   1990.00 </Image>
    <Image> 4850GB_160.fits,4850GB_160.fits,-165.00000,69.9983   -165.00000   69.9983   1990.00 </Image>
    <Image> 4850GB_161.fits,4850GB_161.fits,-155.00000,-0.0017   -155.00000   -0.0017   1990.00 </Image>
    <Image> 4850GB_162.fits,4850GB_162.fits,-155.00000,9.9983   -155.00000   9.9983   1990.00 </Image>
    <Image> 4850GB_163.fits,4850GB_163.fits,-155.00000,19.9983   -155.00000   19.9983   1990.00 </Image>
    <Image> 4850GB_164.fits,4850GB_164.fits,-155.00000,29.9983   -155.00000   29.9983   1990.00 </Image>
    <Image> 4850GB_165.fits,4850GB_165.fits,-155.00000,39.9983   -155.00000   39.9983   1990.00 </Image>
    <Image> 4850GB_166.fits,4850GB_166.fits,-155.00000,49.9983   -155.00000   49.9983   1990.00 </Image>
    <Image> 4850GB_167.fits,4850GB_167.fits,-155.00000,59.9983   -155.00000   59.9983   1990.00 </Image>
    <Image> 4850GB_168.fits,4850GB_168.fits,-155.00000,69.9983   -155.00000   69.9983   1990.00 </Image>
    <Image> 4850GB_169.fits,4850GB_169.fits,-145.00000,-0.0017   -145.00000   -0.0017   1990.00 </Image>
    <Image> 4850GB_17.fits,4850GB_17.fits,25.00000,-0.0017   25.00000   -0.0017   1990.00 </Image>
    <Image> 4850GB_170.fits,4850GB_170.fits,-145.00000,9.9983   -145.00000   9.9983   1990.00 </Image>
    <Image> 4850GB_171.fits,4850GB_171.fits,-145.00000,19.9983   -145.00000   19.9983   1990.00 </Image>
    <Image> 4850GB_172.fits,4850GB_172.fits,-145.00000,29.9983   -145.00000   29.9983   1990.00 </Image>
    <Image> 4850GB_173.fits,4850GB_173.fits,-145.00000,39.9983   -145.00000   39.9983   1990.00 </Image>
    <Image> 4850GB_174.fits,4850GB_174.fits,-145.00000,49.9983   -145.00000   49.9983   1990.00 </Image>
    <Image> 4850GB_175.fits,4850GB_175.fits,-145.00000,59.9983   -145.00000   59.9983   1990.00 </Image>
    <Image> 4850GB_176.fits,4850GB_176.fits,-145.00000,69.9983   -145.00000   69.9983   1990.00 </Image>
    <Image> 4850GB_177.fits,4850GB_177.fits,-135.00000,-0.0017   -135.00000   -0.0017   1990.00 </Image>
    <Image> 4850GB_178.fits,4850GB_178.fits,-135.00000,9.9983   -135.00000   9.9983   1990.00 </Image>
    <Image> 4850GB_179.fits,4850GB_179.fits,-135.00000,19.9983   -135.00000   19.9983   1990.00 </Image>
    <Image> 4850GB_18.fits,4850GB_18.fits,25.00000,9.9983   25.00000   9.9983   1990.00 </Image>
    <Image> 4850GB_180.fits,4850GB_180.fits,-135.00000,29.9983   -135.00000   29.9983   1990.00 </Image>
    <Image> 4850GB_181.fits,4850GB_181.fits,-135.00000,39.9983   -135.00000   39.9983   1990.00 </Image>
    <Image> 4850GB_182.fits,4850GB_182.fits,-135.00000,49.9983   -135.00000   49.9983   1990.00 </Image>
    <Image> 4850GB_183.fits,4850GB_183.fits,-135.00000,59.9983   -135.00000   59.9983   1990.00 </Image>
    <Image> 4850GB_184.fits,4850GB_184.fits,-135.00000,69.9983   -135.00000   69.9983   1990.00 </Image>
    <Image> 4850GB_185.fits,4850GB_185.fits,-125.00000,-0.0017   -125.00000   -0.0017   1990.00 </Image>
    <Image> 4850GB_186.fits,4850GB_186.fits,-125.00000,9.9983   -125.00000   9.9983   1990.00 </Image>
    <Image> 4850GB_187.fits,4850GB_187.fits,-125.00000,19.9983   -125.00000   19.9983   1990.00 </Image>
    <Image> 4850GB_188.fits,4850GB_188.fits,-125.00000,29.9983   -125.00000   29.9983   1990.00 </Image>
    <Image> 4850GB_189.fits,4850GB_189.fits,-125.00000,39.9983   -125.00000   39.9983   1990.00 </Image>
    <Image> 4850GB_19.fits,4850GB_19.fits,25.00000,19.9983   25.00000   19.9983   1990.00 </Image>
    <Image> 4850GB_190.fits,4850GB_190.fits,-125.00000,49.9983   -125.00000   49.9983   1990.00 </Image>
    <Image> 4850GB_191.fits,4850GB_191.fits,-125.00000,59.9983   -125.00000   59.9983   1990.00 </Image>
    <Image> 4850GB_192.fits,4850GB_192.fits,-125.00000,69.9983   -125.00000   69.9983   1990.00 </Image>
    <Image> 4850GB_193.fits,4850GB_193.fits,-114.99999,-0.0017   -114.99999   -0.0017   1990.00 </Image>
    <Image> 4850GB_194.fits,4850GB_194.fits,-114.99999,9.9983   -114.99999   9.9983   1990.00 </Image>
    <Image> 4850GB_195.fits,4850GB_195.fits,-114.99999,19.9983   -114.99999   19.9983   1990.00 </Image>
    <Image> 4850GB_196.fits,4850GB_196.fits,-114.99999,29.9983   -114.99999   29.9983   1990.00 </Image>
    <Image> 4850GB_197.fits,4850GB_197.fits,-114.99999,39.9983   -114.99999   39.9983   1990.00 </Image>
    <Image> 4850GB_198.fits,4850GB_198.fits,-114.99999,49.9983   -114.99999   49.9983   1990.00 </Image>
    <Image> 4850GB_199.fits,4850GB_199.fits,-114.99999,59.9983   -114.99999   59.9983   1990.00 </Image>
    <Image> 4850GB_2.fits,4850GB_2.fits,5.00000,9.9983   5.00000   9.9983   1990.00 </Image>
    <Image> 4850GB_20.fits,4850GB_20.fits,25.00000,29.9983   25.00000   29.9983   1990.00 </Image>
    <Image> 4850GB_200.fits,4850GB_200.fits,-114.99999,69.9983   -114.99999   69.9983   1990.00 </Image>
    <Image> 4850GB_201.fits,4850GB_201.fits,-105.00000,-0.0017   -105.00000   -0.0017   1990.00 </Image>
    <Image> 4850GB_202.fits,4850GB_202.fits,-105.00000,9.9983   -105.00000   9.9983   1990.00 </Image>
    <Image> 4850GB_203.fits,4850GB_203.fits,-105.00000,19.9983   -105.00000   19.9983   1990.00 </Image>
    <Image> 4850GB_204.fits,4850GB_204.fits,-105.00000,29.9983   -105.00000   29.9983   1990.00 </Image>
    <Image> 4850GB_205.fits,4850GB_205.fits,-105.00000,39.9983   -105.00000   39.9983   1990.00 </Image>
    <Image> 4850GB_206.fits,4850GB_206.fits,-105.00000,49.9983   -105.00000   49.9983   1990.00 </Image>
    <Image> 4850GB_207.fits,4850GB_207.fits,-105.00000,59.9983   -105.00000   59.9983   1990.00 </Image>
    <Image> 4850GB_208.fits,4850GB_208.fits,-105.00000,69.9983   -105.00000   69.9983   1990.00 </Image>
    <Image> 4850GB_209.fits,4850GB_209.fits,-95.00000,-0.0017   -95.00000   -0.0017   1990.00 </Image>
    <Image> 4850GB_21.fits,4850GB_21.fits,25.00000,39.9983   25.00000   39.9983   1990.00 </Image>
    <Image> 4850GB_210.fits,4850GB_210.fits,-95.00000,9.9983   -95.00000   9.9983   1990.00 </Image>
    <Image> 4850GB_211.fits,4850GB_211.fits,-95.00000,19.9983   -95.00000   19.9983   1990.00 </Image>
    <Image> 4850GB_212.fits,4850GB_212.fits,-95.00000,29.9983   -95.00000   29.9983   1990.00 </Image>
    <Image> 4850GB_213.fits,4850GB_213.fits,-95.00000,39.9983   -95.00000   39.9983   1990.00 </Image>
    <Image> 4850GB_214.fits,4850GB_214.fits,-95.00000,49.9983   -95.00000   49.9983   1990.00 </Image>
    <Image> 4850GB_215.fits,4850GB_215.fits,-95.00000,59.9983   -95.00000   59.9983   1990.00 </Image>
    <Image> 4850GB_216.fits,4850GB_216.fits,-95.00000,69.9983   -95.00000   69.9983   1990.00 </Image>
    <Image> 4850GB_217.fits,4850GB_217.fits,-85.00000,-0.0017   -85.00000   -0.0017   1990.00 </Image>
    <Image> 4850GB_218.fits,4850GB_218.fits,-85.00000,9.9983   -85.00000   9.9983   1990.00 </Image>
    <Image> 4850GB_219.fits,4850GB_219.fits,-85.00000,19.9983   -85.00000   19.9983   1990.00 </Image>
    <Image> 4850GB_22.fits,4850GB_22.fits,25.00000,49.9983   25.00000   49.9983   1990.00 </Image>
    <Image> 4850GB_220.fits,4850GB_220.fits,-85.00000,29.9983   -85.00000   29.9983   1990.00 </Image>
    <Image> 4850GB_221.fits,4850GB_221.fits,-85.00000,39.9983   -85.00000   39.9983   1990.00 </Image>
    <Image> 4850GB_222.fits,4850GB_222.fits,-85.00000,49.9983   -85.00000   49.9983   1990.00 </Image>
    <Image> 4850GB_223.fits,4850GB_223.fits,-85.00000,59.9983   -85.00000   59.9983   1990.00 </Image>
    <Image> 4850GB_224.fits,4850GB_224.fits,-85.00000,69.9983   -85.00000   69.9983   1990.00 </Image>
    <Image> 4850GB_225.fits,4850GB_225.fits,-75.00000,-0.0017   -75.00000   -0.0017   1990.00 </Image>
    <Image> 4850GB_226.fits,4850GB_226.fits,-75.00000,9.9983   -75.00000   9.9983   1990.00 </Image>
    <Image> 4850GB_227.fits,4850GB_227.fits,-75.00000,19.9983   -75.00000   19.9983   1990.00 </Image>
    <Image> 4850GB_228.fits,4850GB_228.fits,-75.00000,29.9983   -75.00000   29.9983   1990.00 </Image>
    <Image> 4850GB_229.fits,4850GB_229.fits,-75.00000,39.9983   -75.00000   39.9983   1990.00 </Image>
    <Image> 4850GB_23.fits,4850GB_23.fits,25.00000,59.9983   25.00000   59.9983   1990.00 </Image>
    <Image> 4850GB_230.fits,4850GB_230.fits,-75.00000,49.9983   -75.00000   49.9983   1990.00 </Image>
    <Image> 4850GB_231.fits,4850GB_231.fits,-75.00000,59.9983   -75.00000   59.9983   1990.00 </Image>
    <Image> 4850GB_232.fits,4850GB_232.fits,-75.00000,69.9983   -75.00000   69.9983   1990.00 </Image>
    <Image> 4850GB_233.fits,4850GB_233.fits,-65.00000,-0.0017   -65.00000   -0.0017   1990.00 </Image>
    <Image> 4850GB_234.fits,4850GB_234.fits,-65.00000,9.9983   -65.00000   9.9983   1990.00 </Image>
    <Image> 4850GB_235.fits,4850GB_235.fits,-65.00000,19.9983   -65.00000   19.9983   1990.00 </Image>
    <Image> 4850GB_236.fits,4850GB_236.fits,-65.00000,29.9983   -65.00000   29.9983   1990.00 </Image>
    <Image> 4850GB_237.fits,4850GB_237.fits,-65.00000,39.9983   -65.00000   39.9983   1990.00 </Image>
    <Image> 4850GB_238.fits,4850GB_238.fits,-65.00000,49.9983   -65.00000   49.9983   1990.00 </Image>
    <Image> 4850GB_239.fits,4850GB_239.fits,-65.00000,59.9983   -65.00000   59.9983   1990.00 </Image>
    <Image> 4850GB_24.fits,4850GB_24.fits,25.00000,69.9983   25.00000   69.9983   1990.00 </Image>
    <Image> 4850GB_240.fits,4850GB_240.fits,-65.00000,69.9983   -65.00000   69.9983   1990.00 </Image>
    <Image> 4850GB_241.fits,4850GB_241.fits,-55.00000,-0.0017   -55.00000   -0.0017   1990.00 </Image>
    <Image> 4850GB_242.fits,4850GB_242.fits,-55.00000,9.9983   -55.00000   9.9983   1990.00 </Image>
    <Image> 4850GB_243.fits,4850GB_243.fits,-55.00000,19.9983   -55.00000   19.9983   1990.00 </Image>
    <Image> 4850GB_244.fits,4850GB_244.fits,-55.00000,29.9983   -55.00000   29.9983   1990.00 </Image>
    <Image> 4850GB_245.fits,4850GB_245.fits,-55.00000,39.9983   -55.00000   39.9983   1990.00 </Image>
    <Image> 4850GB_246.fits,4850GB_246.fits,-55.00000,49.9983   -55.00000   49.9983   1990.00 </Image>
    <Image> 4850GB_247.fits,4850GB_247.fits,-55.00000,59.9983   -55.00000   59.9983   1990.00 </Image>
    <Image> 4850GB_248.fits,4850GB_248.fits,-55.00000,69.9983   -55.00000   69.9983   1990.00 </Image>
    <Image> 4850GB_249.fits,4850GB_249.fits,-45.00000,-0.0017   -45.00000   -0.0017   1990.00 </Image>
    <Image> 4850GB_25.fits,4850GB_25.fits,35.00000,-0.0017   35.00000   -0.0017   1990.00 </Image>
    <Image> 4850GB_250.fits,4850GB_250.fits,-45.00000,9.9983   -45.00000   9.9983   1990.00 </Image>
    <Image> 4850GB_251.fits,4850GB_251.fits,-45.00000,19.9983   -45.00000   19.9983   1990.00 </Image>
    <Image> 4850GB_252.fits,4850GB_252.fits,-45.00000,29.9983   -45.00000   29.9983   1990.00 </Image>
    <Image> 4850GB_253.fits,4850GB_253.fits,-45.00000,39.9983   -45.00000   39.9983   1990.00 </Image>
    <Image> 4850GB_254.fits,4850GB_254.fits,-45.00000,49.9983   -45.00000   49.9983   1990.00 </Image>
    <Image> 4850GB_255.fits,4850GB_255.fits,-45.00000,59.9983   -45.00000   59.9983   1990.00 </Image>
    <Image> 4850GB_256.fits,4850GB_256.fits,-45.00000,69.9983   -45.00000   69.9983   1990.00 </Image>
    <Image> 4850GB_257.fits,4850GB_257.fits,-35.00000,-0.0017   -35.00000   -0.0017   1990.00 </Image>
    <Image> 4850GB_258.fits,4850GB_258.fits,-35.00000,9.9983   -35.00000   9.9983   1990.00 </Image>
    <Image> 4850GB_259.fits,4850GB_259.fits,-35.00000,19.9983   -35.00000   19.9983   1990.00 </Image>
    <Image> 4850GB_26.fits,4850GB_26.fits,35.00000,9.9983   35.00000   9.9983   1990.00 </Image>
    <Image> 4850GB_260.fits,4850GB_260.fits,-35.00000,29.9983   -35.00000   29.9983   1990.00 </Image>
    <Image> 4850GB_261.fits,4850GB_261.fits,-35.00000,39.9983   -35.00000   39.9983   1990.00 </Image>
    <Image> 4850GB_262.fits,4850GB_262.fits,-35.00000,49.9983   -35.00000   49.9983   1990.00 </Image>
    <Image> 4850GB_263.fits,4850GB_263.fits,-35.00000,59.9983   -35.00000   59.9983   1990.00 </Image>
    <Image> 4850GB_264.fits,4850GB_264.fits,-35.00000,69.9983   -35.00000   69.9983   1990.00 </Image>
    <Image> 4850GB_265.fits,4850GB_265.fits,-25.00000,-0.0017   -25.00000   -0.0017   1990.00 </Image>
    <Image> 4850GB_266.fits,4850GB_266.fits,-25.00000,9.9983   -25.00000   9.9983   1990.00 </Image>
    <Image> 4850GB_267.fits,4850GB_267.fits,-25.00000,19.9983   -25.00000   19.9983   1990.00 </Image>
    <Image> 4850GB_268.fits,4850GB_268.fits,-25.00000,29.9983   -25.00000   29.9983   1990.00 </Image>
    <Image> 4850GB_269.fits,4850GB_269.fits,-25.00000,39.9983   -25.00000   39.9983   1990.00 </Image>
    <Image> 4850GB_27.fits,4850GB_27.fits,35.00000,19.9983   35.00000   19.9983   1990.00 </Image>
    <Image> 4850GB_270.fits,4850GB_270.fits,-25.00000,49.9983   -25.00000   49.9983   1990.00 </Image>
    <Image> 4850GB_271.fits,4850GB_271.fits,-25.00000,59.9983   -25.00000   59.9983   1990.00 </Image>
    <Image> 4850GB_272.fits,4850GB_272.fits,-25.00000,69.9983   -25.00000   69.9983   1990.00 </Image>
    <Image> 4850GB_273.fits,4850GB_273.fits,-15.00000,-0.0017   -15.00000   -0.0017   1990.00 </Image>
    <Image> 4850GB_274.fits,4850GB_274.fits,-15.00000,9.9983   -15.00000   9.9983   1990.00 </Image>
    <Image> 4850GB_275.fits,4850GB_275.fits,-15.00000,19.9983   -15.00000   19.9983   1990.00 </Image>
    <Image> 4850GB_276.fits,4850GB_276.fits,-15.00000,29.9983   -15.00000   29.9983   1990.00 </Image>
    <Image> 4850GB_277.fits,4850GB_277.fits,-15.00000,39.9983   -15.00000   39.9983   1990.00 </Image>
    <Image> 4850GB_278.fits,4850GB_278.fits,-15.00000,49.9983   -15.00000   49.9983   1990.00 </Image>
    <Image> 4850GB_279.fits,4850GB_279.fits,-15.00000,59.9983   -15.00000   59.9983   1990.00 </Image>
    <Image> 4850GB_28.fits,4850GB_28.fits,35.00000,29.9983   35.00000   29.9983   1990.00 </Image>
    <Image> 4850GB_280.fits,4850GB_280.fits,-15.00000,69.9983   -15.00000   69.9983   1990.00 </Image>
    <Image> 4850GB_281.fits,4850GB_281.fits,-5.00000,-0.0017   -5.00000   -0.0017   1990.00 </Image>
    <Image> 4850GB_282.fits,4850GB_282.fits,-5.00000,9.9983   -5.00000   9.9983   1990.00 </Image>
    <Image> 4850GB_283.fits,4850GB_283.fits,-5.00000,19.9983   -5.00000   19.9983   1990.00 </Image>
    <Image> 4850GB_284.fits,4850GB_284.fits,-5.00000,29.9983   -5.00000   29.9983   1990.00 </Image>
    <Image> 4850GB_285.fits,4850GB_285.fits,-5.00000,39.9983   -5.00000   39.9983   1990.00 </Image>
    <Image> 4850GB_286.fits,4850GB_286.fits,-5.00000,49.9983   -5.00000   49.9983   1990.00 </Image>
    <Image> 4850GB_287.fits,4850GB_287.fits,-5.00000,59.9983   -5.00000   59.9983   1990.00 </Image>
    <Image> 4850GB_288.fits,4850GB_288.fits,-5.00000,69.9983   -5.00000   69.9983   1990.00 </Image>
    <Image> 4850GB_29.fits,4850GB_29.fits,35.00000,39.9983   35.00000   39.9983   1990.00 </Image>
    <Image> 4850GB_3.fits,4850GB_3.fits,5.00000,19.9983   5.00000   19.9983   1990.00 </Image>
    <Image> 4850GB_30.fits,4850GB_30.fits,35.00000,49.9983   35.00000   49.9983   1990.00 </Image>
    <Image> 4850GB_31.fits,4850GB_31.fits,35.00000,59.9983   35.00000   59.9983   1990.00 </Image>
    <Image> 4850GB_32.fits,4850GB_32.fits,35.00000,69.9983   35.00000   69.9983   1990.00 </Image>
    <Image> 4850GB_33.fits,4850GB_33.fits,45.00000,-0.0017   45.00000   -0.0017   1990.00 </Image>
    <Image> 4850GB_34.fits,4850GB_34.fits,45.00000,9.9983   45.00000   9.9983   1990.00 </Image>
    <Image> 4850GB_35.fits,4850GB_35.fits,45.00000,19.9983   45.00000   19.9983   1990.00 </Image>
    <Image> 4850GB_36.fits,4850GB_36.fits,45.00000,29.9983   45.00000   29.9983   1990.00 </Image>
    <Image> 4850GB_37.fits,4850GB_37.fits,45.00000,39.9983   45.00000   39.9983   1990.00 </Image>
    <Image> 4850GB_38.fits,4850GB_38.fits,45.00000,49.9983   45.00000   49.9983   1990.00 </Image>
    <Image> 4850GB_39.fits,4850GB_39.fits,45.00000,59.9983   45.00000   59.9983   1990.00 </Image>
    <Image> 4850GB_4.fits,4850GB_4.fits,5.00000,29.9983   5.00000   29.9983   1990.00 </Image>
    <Image> 4850GB_40.fits,4850GB_40.fits,45.00000,69.9983   45.00000   69.9983   1990.00 </Image>
    <Image> 4850GB_41.fits,4850GB_41.fits,55.00000,-0.0017   55.00000   -0.0017   1990.00 </Image>
    <Image> 4850GB_42.fits,4850GB_42.fits,55.00000,9.9983   55.00000   9.9983   1990.00 </Image>
    <Image> 4850GB_43.fits,4850GB_43.fits,55.00000,19.9983   55.00000   19.9983   1990.00 </Image>
    <Image> 4850GB_44.fits,4850GB_44.fits,55.00000,29.9983   55.00000   29.9983   1990.00 </Image>
    <Image> 4850GB_45.fits,4850GB_45.fits,55.00000,39.9983   55.00000   39.9983   1990.00 </Image>
    <Image> 4850GB_46.fits,4850GB_46.fits,55.00000,49.9983   55.00000   49.9983   1990.00 </Image>
    <Image> 4850GB_47.fits,4850GB_47.fits,55.00000,59.9983   55.00000   59.9983   1990.00 </Image>
    <Image> 4850GB_48.fits,4850GB_48.fits,55.00000,69.9983   55.00000   69.9983   1990.00 </Image>
    <Image> 4850GB_49.fits,4850GB_49.fits,65.00000,-0.0017   65.00000   -0.0017   1990.00 </Image>
    <Image> 4850GB_5.fits,4850GB_5.fits,5.00000,39.9983   5.00000   39.9983   1990.00 </Image>
    <Image> 4850GB_50.fits,4850GB_50.fits,65.00000,9.9983   65.00000   9.9983   1990.00 </Image>
    <Image> 4850GB_51.fits,4850GB_51.fits,65.00000,19.9983   65.00000   19.9983   1990.00 </Image>
    <Image> 4850GB_52.fits,4850GB_52.fits,65.00000,29.9983   65.00000   29.9983   1990.00 </Image>
    <Image> 4850GB_53.fits,4850GB_53.fits,65.00000,39.9983   65.00000   39.9983   1990.00 </Image>
    <Image> 4850GB_54.fits,4850GB_54.fits,65.00000,49.9983   65.00000   49.9983   1990.00 </Image>
    <Image> 4850GB_55.fits,4850GB_55.fits,65.00000,59.9983   65.00000   59.9983   1990.00 </Image>
    <Image> 4850GB_56.fits,4850GB_56.fits,65.00000,69.9983   65.00000   69.9983   1990.00 </Image>
    <Image> 4850GB_57.fits,4850GB_57.fits,75.00000,-0.0017   75.00000   -0.0017   1990.00 </Image>
    <Image> 4850GB_58.fits,4850GB_58.fits,75.00000,9.9983   75.00000   9.9983   1990.00 </Image>
    <Image> 4850GB_59.fits,4850GB_59.fits,75.00000,19.9983   75.00000   19.9983   1990.00 </Image>
    <Image> 4850GB_6.fits,4850GB_6.fits,5.00000,49.9983   5.00000   49.9983   1990.00 </Image>
    <Image> 4850GB_60.fits,4850GB_60.fits,75.00000,29.9983   75.00000   29.9983   1990.00 </Image>
    <Image> 4850GB_61.fits,4850GB_61.fits,75.00000,39.9983   75.00000   39.9983   1990.00 </Image>
    <Image> 4850GB_62.fits,4850GB_62.fits,75.00000,49.9983   75.00000   49.9983   1990.00 </Image>
    <Image> 4850GB_63.fits,4850GB_63.fits,75.00000,59.9983   75.00000   59.9983   1990.00 </Image>
    <Image> 4850GB_64.fits,4850GB_64.fits,75.00000,69.9983   75.00000   69.9983   1990.00 </Image>
    <Image> 4850GB_65.fits,4850GB_65.fits,85.00000,-0.0017   85.00000   -0.0017   1990.00 </Image>
    <Image> 4850GB_66.fits,4850GB_66.fits,85.00000,9.9983   85.00000   9.9983   1990.00 </Image>
    <Image> 4850GB_67.fits,4850GB_67.fits,85.00000,19.9983   85.00000   19.9983   1990.00 </Image>
    <Image> 4850GB_68.fits,4850GB_68.fits,85.00000,29.9983   85.00000   29.9983   1990.00 </Image>
    <Image> 4850GB_69.fits,4850GB_69.fits,85.00000,39.9983   85.00000   39.9983   1990.00 </Image>
    <Image> 4850GB_7.fits,4850GB_7.fits,5.00000,59.9983   5.00000   59.9983   1990.00 </Image>
    <Image> 4850GB_70.fits,4850GB_70.fits,85.00000,49.9983   85.00000   49.9983   1990.00 </Image>
    <Image> 4850GB_71.fits,4850GB_71.fits,85.00000,59.9983   85.00000   59.9983   1990.00 </Image>
    <Image> 4850GB_72.fits,4850GB_72.fits,85.00000,69.9983   85.00000   69.9983   1990.00 </Image>
    <Image> 4850GB_73.fits,4850GB_73.fits,95.00000,-0.0017   95.00000   -0.0017   1990.00 </Image>
    <Image> 4850GB_74.fits,4850GB_74.fits,95.00000,9.9983   95.00000   9.9983   1990.00 </Image>
    <Image> 4850GB_75.fits,4850GB_75.fits,95.00000,19.9983   95.00000   19.9983   1990.00 </Image>
    <Image> 4850GB_76.fits,4850GB_76.fits,95.00000,29.9983   95.00000   29.9983   1990.00 </Image>
    <Image> 4850GB_77.fits,4850GB_77.fits,95.00000,39.9983   95.00000   39.9983   1990.00 </Image>
    <Image> 4850GB_78.fits,4850GB_78.fits,95.00000,49.9983   95.00000   49.9983   1990.00 </Image>
    <Image> 4850GB_79.fits,4850GB_79.fits,95.00000,59.9983   95.00000   59.9983   1990.00 </Image>
    <Image> 4850GB_8.fits,4850GB_8.fits,5.00000,69.9983   5.00000   69.9983   1990.00 </Image>
    <Image> 4850GB_80.fits,4850GB_80.fits,95.00000,69.9983   95.00000   69.9983   1990.00 </Image>
    <Image> 4850GB_81.fits,4850GB_81.fits,105.00000,-0.0017   105.00000   -0.0017   1990.00 </Image>
    <Image> 4850GB_82.fits,4850GB_82.fits,105.00000,9.9983   105.00000   9.9983   1990.00 </Image>
    <Image> 4850GB_83.fits,4850GB_83.fits,105.00000,19.9983   105.00000   19.9983   1990.00 </Image>
    <Image> 4850GB_84.fits,4850GB_84.fits,105.00000,29.9983   105.00000   29.9983   1990.00 </Image>
    <Image> 4850GB_85.fits,4850GB_85.fits,105.00000,39.9983   105.00000   39.9983   1990.00 </Image>
    <Image> 4850GB_86.fits,4850GB_86.fits,105.00000,49.9983   105.00000   49.9983   1990.00 </Image>
    <Image> 4850GB_87.fits,4850GB_87.fits,105.00000,59.9983   105.00000   59.9983   1990.00 </Image>
    <Image> 4850GB_88.fits,4850GB_88.fits,105.00000,69.9983   105.00000   69.9983   1990.00 </Image>
    <Image> 4850GB_89.fits,4850GB_89.fits,115.00000,-0.0017   115.00000   -0.0017   1990.00 </Image>
    <Image> 4850GB_9.fits,4850GB_9.fits,15.00000,-0.0017   15.00000   -0.0017   1990.00 </Image>
    <Image> 4850GB_90.fits,4850GB_90.fits,115.00000,9.9983   115.00000   9.9983   1990.00 </Image>
    <Image> 4850GB_91.fits,4850GB_91.fits,115.00000,19.9983   115.00000   19.9983   1990.00 </Image>
    <Image> 4850GB_92.fits,4850GB_92.fits,115.00000,29.9983   115.00000   29.9983   1990.00 </Image>
    <Image> 4850GB_93.fits,4850GB_93.fits,115.00000,39.9983   115.00000   39.9983   1990.00 </Image>
    <Image> 4850GB_94.fits,4850GB_94.fits,115.00000,49.9983   115.00000   49.9983   1990.00 </Image>
    <Image> 4850GB_95.fits,4850GB_95.fits,115.00000,59.9983   115.00000   59.9983   1990.00 </Image>
    <Image> 4850GB_96.fits,4850GB_96.fits,115.00000,69.9983   115.00000   69.9983   1990.00 </Image>
    <Image> 4850GB_97.fits,4850GB_97.fits,124.99999,-0.0017   124.99999   -0.0017   1990.00 </Image>
    <Image> 4850GB_98.fits,4850GB_98.fits,124.99999,9.9983   124.99999   9.9983   1990.00 </Image>
    <Image> 4850GB_99.fits,4850GB_99.fits,124.99999,19.9983   124.99999   19.9983   1990.00 </Image>
    <Image> 4850pmn_1.fits,4850pmn_1.fits,7.50000,-9.9348   7.50000   -9.9348   1990.00 </Image>
    <Image> 4850pmn_10.fits,4850pmn_10.fits,22.50000,-49.9348   22.50000   -49.9348   1990.00 </Image>
    <Image> 4850pmn_100.fits,4850pmn_100.fits,-112.50000,-49.9348   -112.50000   -49.9348   1990.00 </Image>
    <Image> 4850pmn_101.fits,4850pmn_101.fits,-112.50000,-64.9348   -112.50000   -64.9348   1990.00 </Image>
    <Image> 4850pmn_102.fits,4850pmn_102.fits,-112.50000,-79.9348   -112.50000   -79.9348   1990.00 </Image>
    <Image> 4850pmn_103.fits,4850pmn_103.fits,-97.50000,-9.9348   -97.50000   -9.9348   1990.00 </Image>
    <Image> 4850pmn_104.fits,4850pmn_104.fits,-97.50000,-24.9348   -97.50000   -24.9348   1990.00 </Image>
    <Image> 4850pmn_105.fits,4850pmn_105.fits,-97.50000,-34.9348   -97.50000   -34.9348   1990.00 </Image>
    <Image> 4850pmn_106.fits,4850pmn_106.fits,-97.50000,-49.9348   -97.50000   -49.9348   1990.00 </Image>
    <Image> 4850pmn_107.fits,4850pmn_107.fits,-97.50000,-64.9348   -97.50000   -64.9348   1990.00 </Image>
    <Image> 4850pmn_108.fits,4850pmn_108.fits,-97.50000,-79.9348   -97.50000   -79.9348   1990.00 </Image>
    <Image> 4850pmn_109.fits,4850pmn_109.fits,-82.50000,-9.9348   -82.50000   -9.9348   1990.00 </Image>
    <Image> 4850pmn_11.fits,4850pmn_11.fits,22.50000,-64.9348   22.50000   -64.9348   1990.00 </Image>
    <Image> 4850pmn_110.fits,4850pmn_110.fits,-82.50000,-24.9348   -82.50000   -24.9348   1990.00 </Image>
    <Image> 4850pmn_111.fits,4850pmn_111.fits,-82.50000,-34.9348   -82.50000   -34.9348   1990.00 </Image>
    <Image> 4850pmn_112.fits,4850pmn_112.fits,-82.50000,-49.9348   -82.50000   -49.9348   1990.00 </Image>
    <Image> 4850pmn_113.fits,4850pmn_113.fits,-82.50000,-64.9348   -82.50000   -64.9348   1990.00 </Image>
    <Image> 4850pmn_114.fits,4850pmn_114.fits,-82.50000,-79.9348   -82.50000   -79.9348   1990.00 </Image>
    <Image> 4850pmn_115.fits,4850pmn_115.fits,-67.50000,-9.9348   -67.50000   -9.9348   1990.00 </Image>
    <Image> 4850pmn_116.fits,4850pmn_116.fits,-67.50000,-24.9348   -67.50000   -24.9348   1990.00 </Image>
    <Image> 4850pmn_117.fits,4850pmn_117.fits,-67.50000,-34.9348   -67.50000   -34.9348   1990.00 </Image>
    <Image> 4850pmn_118.fits,4850pmn_118.fits,-67.50000,-49.9348   -67.50000   -49.9348   1990.00 </Image>
    <Image> 4850pmn_119.fits,4850pmn_119.fits,-67.50000,-64.9348   -67.50000   -64.9348   1990.00 </Image>
    <Image> 4850pmn_12.fits,4850pmn_12.fits,22.50000,-79.9348   22.50000   -79.9348   1990.00 </Image>
    <Image> 4850pmn_120.fits,4850pmn_120.fits,-67.50000,-79.9348   -67.50000   -79.9348   1990.00 </Image>
    <Image> 4850pmn_121.fits,4850pmn_121.fits,-52.50000,-9.9348   -52.50000   -9.9348   1990.00 </Image>
    <Image> 4850pmn_122.fits,4850pmn_122.fits,-52.50000,-24.9348   -52.50000   -24.9348   1990.00 </Image>
    <Image> 4850pmn_123.fits,4850pmn_123.fits,-52.50000,-34.9348   -52.50000   -34.9348   1990.00 </Image>
    <Image> 4850pmn_124.fits,4850pmn_124.fits,-52.50000,-49.9348   -52.50000   -49.9348   1990.00 </Image>
    <Image> 4850pmn_125.fits,4850pmn_125.fits,-52.50000,-64.9348   -52.50000   -64.9348   1990.00 </Image>
    <Image> 4850pmn_126.fits,4850pmn_126.fits,-52.50000,-79.9348   -52.50000   -79.9348   1990.00 </Image>
    <Image> 4850pmn_127.fits,4850pmn_127.fits,-37.50000,-9.9348   -37.50000   -9.9348   1990.00 </Image>
    <Image> 4850pmn_128.fits,4850pmn_128.fits,-37.50000,-24.9348   -37.50000   -24.9348   1990.00 </Image>
    <Image> 4850pmn_129.fits,4850pmn_129.fits,-37.50000,-34.9348   -37.50000   -34.9348   1990.00 </Image>
    <Image> 4850pmn_13.fits,4850pmn_13.fits,37.50000,-9.9348   37.50000   -9.9348   1990.00 </Image>
    <Image> 4850pmn_130.fits,4850pmn_130.fits,-37.50000,-49.9348   -37.50000   -49.9348   1990.00 </Image>
    <Image> 4850pmn_131.fits,4850pmn_131.fits,-37.50000,-64.9348   -37.50000   -64.9348   1990.00 </Image>
    <Image> 4850pmn_132.fits,4850pmn_132.fits,-37.50000,-79.9348   -37.50000   -79.9348   1990.00 </Image>
    <Image> 4850pmn_133.fits,4850pmn_133.fits,-22.50000,-9.9348   -22.50000   -9.9348   1990.00 </Image>
    <Image> 4850pmn_134.fits,4850pmn_134.fits,-22.50000,-24.9348   -22.50000   -24.9348   1990.00 </Image>
    <Image> 4850pmn_135.fits,4850pmn_135.fits,-22.50000,-34.9348   -22.50000   -34.9348   1990.00 </Image>
    <Image> 4850pmn_136.fits,4850pmn_136.fits,-22.50000,-49.9348   -22.50000   -49.9348   1990.00 </Image>
    <Image> 4850pmn_137.fits,4850pmn_137.fits,-22.50000,-64.9348   -22.50000   -64.9348   1990.00 </Image>
    <Image> 4850pmn_138.fits,4850pmn_138.fits,-22.50000,-79.9348   -22.50000   -79.9348   1990.00 </Image>
    <Image> 4850pmn_139.fits,4850pmn_139.fits,-7.50000,-9.9348   -7.50000   -9.9348   1990.00 </Image>
    <Image> 4850pmn_14.fits,4850pmn_14.fits,37.50000,-24.9348   37.50000   -24.9348   1990.00 </Image>
    <Image> 4850pmn_140.fits,4850pmn_140.fits,-7.50000,-24.9348   -7.50000   -24.9348   1990.00 </Image>
    <Image> 4850pmn_141.fits,4850pmn_141.fits,-7.50000,-34.9348   -7.50000   -34.9348   1990.00 </Image>
    <Image> 4850pmn_142.fits,4850pmn_142.fits,-7.50000,-49.9348   -7.50000   -49.9348   1990.00 </Image>
    <Image> 4850pmn_143.fits,4850pmn_143.fits,-7.50000,-64.9348   -7.50000   -64.9348   1990.00 </Image>
    <Image> 4850pmn_144.fits,4850pmn_144.fits,-7.50000,-79.9348   -7.50000   -79.9348   1990.00 </Image>
    <Image> 4850pmn_15.fits,4850pmn_15.fits,37.50000,-34.9348   37.50000   -34.9348   1990.00 </Image>
    <Image> 4850pmn_16.fits,4850pmn_16.fits,37.50000,-49.9348   37.50000   -49.9348   1990.00 </Image>
    <Image> 4850pmn_17.fits,4850pmn_17.fits,37.50000,-64.9348   37.50000   -64.9348   1990.00 </Image>
    <Image> 4850pmn_18.fits,4850pmn_18.fits,37.50000,-79.9348   37.50000   -79.9348   1990.00 </Image>
    <Image> 4850pmn_19.fits,4850pmn_19.fits,52.50000,-9.9348   52.50000   -9.9348   1990.00 </Image>
    <Image> 4850pmn_2.fits,4850pmn_2.fits,7.50000,-24.9348   7.50000   -24.9348   1990.00 </Image>
    <Image> 4850pmn_20.fits,4850pmn_20.fits,52.50000,-24.9348   52.50000   -24.9348   1990.00 </Image>
    <Image> 4850pmn_21.fits,4850pmn_21.fits,52.50000,-34.9348   52.50000   -34.9348   1990.00 </Image>
    <Image> 4850pmn_22.fits,4850pmn_22.fits,52.50000,-49.9348   52.50000   -49.9348   1990.00 </Image>
    <Image> 4850pmn_23.fits,4850pmn_23.fits,52.50000,-64.9348   52.50000   -64.9348   1990.00 </Image>
    <Image> 4850pmn_24.fits,4850pmn_24.fits,52.50000,-79.9348   52.50000   -79.9348   1990.00 </Image>
    <Image> 4850pmn_25.fits,4850pmn_25.fits,67.50000,-9.9348   67.50000   -9.9348   1990.00 </Image>
    <Image> 4850pmn_26.fits,4850pmn_26.fits,67.50000,-24.9348   67.50000   -24.9348   1990.00 </Image>
    <Image> 4850pmn_27.fits,4850pmn_27.fits,67.50000,-34.9348   67.50000   -34.9348   1990.00 </Image>
    <Image> 4850pmn_28.fits,4850pmn_28.fits,67.50000,-49.9348   67.50000   -49.9348   1990.00 </Image>
    <Image> 4850pmn_29.fits,4850pmn_29.fits,67.50000,-64.9348   67.50000   -64.9348   1990.00 </Image>
    <Image> 4850pmn_3.fits,4850pmn_3.fits,7.50000,-34.9348   7.50000   -34.9348   1990.00 </Image>
    <Image> 4850pmn_30.fits,4850pmn_30.fits,67.50000,-79.9348   67.50000   -79.9348   1990.00 </Image>
    <Image> 4850pmn_31.fits,4850pmn_31.fits,82.50000,-9.9348   82.50000   -9.9348   1990.00 </Image>
    <Image> 4850pmn_32.fits,4850pmn_32.fits,82.50000,-24.9348   82.50000   -24.9348   1990.00 </Image>
    <Image> 4850pmn_33.fits,4850pmn_33.fits,82.50000,-34.9348   82.50000   -34.9348   1990.00 </Image>
    <Image> 4850pmn_34.fits,4850pmn_34.fits,82.50000,-49.9348   82.50000   -49.9348   1990.00 </Image>
    <Image> 4850pmn_35.fits,4850pmn_35.fits,82.50000,-64.9348   82.50000   -64.9348   1990.00 </Image>
    <Image> 4850pmn_36.fits,4850pmn_36.fits,82.50000,-79.9348   82.50000   -79.9348   1990.00 </Image>
    <Image> 4850pmn_37.fits,4850pmn_37.fits,97.50000,-9.9348   97.50000   -9.9348   1990.00 </Image>
    <Image> 4850pmn_38.fits,4850pmn_38.fits,97.50000,-24.9348   97.50000   -24.9348   1990.00 </Image>
    <Image> 4850pmn_39.fits,4850pmn_39.fits,97.50000,-34.9348   97.50000   -34.9348   1990.00 </Image>
    <Image> 4850pmn_4.fits,4850pmn_4.fits,7.50000,-49.9348   7.50000   -49.9348   1990.00 </Image>
    <Image> 4850pmn_40.fits,4850pmn_40.fits,97.50000,-49.9348   97.50000   -49.9348   1990.00 </Image>
    <Image> 4850pmn_41.fits,4850pmn_41.fits,97.50000,-64.9348   97.50000   -64.9348   1990.00 </Image>
    <Image> 4850pmn_42.fits,4850pmn_42.fits,97.50000,-79.9348   97.50000   -79.9348   1990.00 </Image>
    <Image> 4850pmn_43.fits,4850pmn_43.fits,112.50000,-9.9348   112.50000   -9.9348   1990.00 </Image>
    <Image> 4850pmn_44.fits,4850pmn_44.fits,112.50000,-24.9348   112.50000   -24.9348   1990.00 </Image>
    <Image> 4850pmn_45.fits,4850pmn_45.fits,112.50000,-34.9348   112.50000   -34.9348   1990.00 </Image>
    <Image> 4850pmn_46.fits,4850pmn_46.fits,112.50000,-49.9348   112.50000   -49.9348   1990.00 </Image>
    <Image> 4850pmn_47.fits,4850pmn_47.fits,112.50000,-64.9348   112.50000   -64.9348   1990.00 </Image>
    <Image> 4850pmn_48.fits,4850pmn_48.fits,112.50000,-79.9348   112.50000   -79.9348   1990.00 </Image>
    <Image> 4850pmn_49.fits,4850pmn_49.fits,127.50000,-9.9348   127.50000   -9.9348   1990.00 </Image>
    <Image> 4850pmn_5.fits,4850pmn_5.fits,7.50000,-64.9348   7.50000   -64.9348   1990.00 </Image>
    <Image> 4850pmn_50.fits,4850pmn_50.fits,127.50000,-24.9348   127.50000   -24.9348   1990.00 </Image>
    <Image> 4850pmn_51.fits,4850pmn_51.fits,127.50000,-34.9348   127.50000   -34.9348   1990.00 </Image>
    <Image> 4850pmn_52.fits,4850pmn_52.fits,127.50000,-49.9348   127.50000   -49.9348   1990.00 </Image>
    <Image> 4850pmn_53.fits,4850pmn_53.fits,127.50000,-64.9348   127.50000   -64.9348   1990.00 </Image>
    <Image> 4850pmn_54.fits,4850pmn_54.fits,127.50000,-79.9348   127.50000   -79.9348   1990.00 </Image>
    <Image> 4850pmn_55.fits,4850pmn_55.fits,142.50000,-9.9348   142.50000   -9.9348   1990.00 </Image>
    <Image> 4850pmn_56.fits,4850pmn_56.fits,142.50000,-24.9348   142.50000   -24.9348   1990.00 </Image>
    <Image> 4850pmn_57.fits,4850pmn_57.fits,142.50000,-34.9348   142.50000   -34.9348   1990.00 </Image>
    <Image> 4850pmn_58.fits,4850pmn_58.fits,142.50000,-49.9348   142.50000   -49.9348   1990.00 </Image>
    <Image> 4850pmn_59.fits,4850pmn_59.fits,142.50000,-64.9348   142.50000   -64.9348   1990.00 </Image>
    <Image> 4850pmn_6.fits,4850pmn_6.fits,7.50000,-79.9348   7.50000   -79.9348   1990.00 </Image>
    <Image> 4850pmn_60.fits,4850pmn_60.fits,142.50000,-79.9348   142.50000   -79.9348   1990.00 </Image>
    <Image> 4850pmn_61.fits,4850pmn_61.fits,157.50000,-9.9348   157.50000   -9.9348   1990.00 </Image>
    <Image> 4850pmn_62.fits,4850pmn_62.fits,157.50000,-24.9348   157.50000   -24.9348   1990.00 </Image>
    <Image> 4850pmn_63.fits,4850pmn_63.fits,157.50000,-34.9348   157.50000   -34.9348   1990.00 </Image>
    <Image> 4850pmn_64.fits,4850pmn_64.fits,157.50000,-49.9348   157.50000   -49.9348   1990.00 </Image>
    <Image> 4850pmn_65.fits,4850pmn_65.fits,157.50000,-64.9348   157.50000   -64.9348   1990.00 </Image>
    <Image> 4850pmn_66.fits,4850pmn_66.fits,157.50000,-79.9348   157.50000   -79.9348   1990.00 </Image>
    <Image> 4850pmn_67.fits,4850pmn_67.fits,172.50000,-9.9348   172.50000   -9.9348   1990.00 </Image>
    <Image> 4850pmn_68.fits,4850pmn_68.fits,172.50000,-24.9348   172.50000   -24.9348   1990.00 </Image>
    <Image> 4850pmn_69.fits,4850pmn_69.fits,172.50000,-34.9348   172.50000   -34.9348   1990.00 </Image>
    <Image> 4850pmn_7.fits,4850pmn_7.fits,22.50000,-9.9348   22.50000   -9.9348   1990.00 </Image>
    <Image> 4850pmn_70.fits,4850pmn_70.fits,172.50000,-49.9348   172.50000   -49.9348   1990.00 </Image>
    <Image> 4850pmn_71.fits,4850pmn_71.fits,172.50000,-64.9348   172.50000   -64.9348   1990.00 </Image>
    <Image> 4850pmn_72.fits,4850pmn_72.fits,172.50000,-79.9348   172.50000   -79.9348   1990.00 </Image>
    <Image> 4850pmn_73.fits,4850pmn_73.fits,-172.50000,-9.9348   -172.50000   -9.9348   1990.00 </Image>
    <Image> 4850pmn_74.fits,4850pmn_74.fits,-172.50000,-24.9348   -172.50000   -24.9348   1990.00 </Image>
    <Image> 4850pmn_75.fits,4850pmn_75.fits,-172.50000,-34.9348   -172.50000   -34.9348   1990.00 </Image>
    <Image> 4850pmn_76.fits,4850pmn_76.fits,-172.50000,-49.9348   -172.50000   -49.9348   1990.00 </Image>
    <Image> 4850pmn_77.fits,4850pmn_77.fits,-172.50000,-64.9348   -172.50000   -64.9348   1990.00 </Image>
    <Image> 4850pmn_78.fits,4850pmn_78.fits,-172.50000,-79.9348   -172.50000   -79.9348   1990.00 </Image>
    <Image> 4850pmn_79.fits,4850pmn_79.fits,-157.50000,-9.9348   -157.50000   -9.9348   1990.00 </Image>
    <Image> 4850pmn_8.fits,4850pmn_8.fits,22.50000,-24.9348   22.50000   -24.9348   1990.00 </Image>
    <Image> 4850pmn_80.fits,4850pmn_80.fits,-157.50000,-24.9348   -157.50000   -24.9348   1990.00 </Image>
    <Image> 4850pmn_81.fits,4850pmn_81.fits,-157.50000,-34.9348   -157.50000   -34.9348   1990.00 </Image>
    <Image> 4850pmn_82.fits,4850pmn_82.fits,-157.50000,-49.9348   -157.50000   -49.9348   1990.00 </Image>
    <Image> 4850pmn_83.fits,4850pmn_83.fits,-157.50000,-64.9348   -157.50000   -64.9348   1990.00 </Image>
    <Image> 4850pmn_84.fits,4850pmn_84.fits,-157.50000,-79.9348   -157.50000   -79.9348   1990.00 </Image>
    <Image> 4850pmn_85.fits,4850pmn_85.fits,-142.50000,-9.9348   -142.50000   -9.9348   1990.00 </Image>
    <Image> 4850pmn_86.fits,4850pmn_86.fits,-142.50000,-24.9348   -142.50000   -24.9348   1990.00 </Image>
    <Image> 4850pmn_87.fits,4850pmn_87.fits,-142.50000,-34.9348   -142.50000   -34.9348   1990.00 </Image>
    <Image> 4850pmn_88.fits,4850pmn_88.fits,-142.50000,-49.9348   -142.50000   -49.9348   1990.00 </Image>
    <Image> 4850pmn_89.fits,4850pmn_89.fits,-142.50000,-64.9348   -142.50000   -64.9348   1990.00 </Image>
    <Image> 4850pmn_9.fits,4850pmn_9.fits,22.50000,-34.9348   22.50000   -34.9348   1990.00 </Image>
    <Image> 4850pmn_90.fits,4850pmn_90.fits,-142.50000,-79.9348   -142.50000   -79.9348   1990.00 </Image>
    <Image> 4850pmn_91.fits,4850pmn_91.fits,-127.50000,-9.9348   -127.50000   -9.9348   1990.00 </Image>
    <Image> 4850pmn_92.fits,4850pmn_92.fits,-127.50000,-24.9348   -127.50000   -24.9348   1990.00 </Image>
    <Image> 4850pmn_93.fits,4850pmn_93.fits,-127.50000,-34.9348   -127.50000   -34.9348   1990.00 </Image>
    <Image> 4850pmn_94.fits,4850pmn_94.fits,-127.50000,-49.9348   -127.50000   -49.9348   1990.00 </Image>
    <Image> 4850pmn_95.fits,4850pmn_95.fits,-127.50000,-64.9348   -127.50000   -64.9348   1990.00 </Image>
    <Image> 4850pmn_96.fits,4850pmn_96.fits,-127.50000,-79.9348   -127.50000   -79.9348   1990.00 </Image>
    <Image> 4850pmn_97.fits,4850pmn_97.fits,-112.50000,-9.9348   -112.50000   -9.9348   1990.00 </Image>
    <Image> 4850pmn_98.fits,4850pmn_98.fits,-112.50000,-24.9348   -112.50000   -24.9348   1990.00 </Image>
    <Image> 4850pmn_99.fits,4850pmn_99.fits,-112.50000,-34.9348   -112.50000   -34.9348   1990.00 </Image>
  </Images>
</Survey>
